pibooth_qrcode.py
pibooth_qrcode-1.0.2.dist-info/LICENSE
pibooth_qrcode-1.0.2.dist-info/METADATA
pibooth_qrcode-1.0.2.dist-info/WHEEL
pibooth_qrcode-1.0.2.dist-info/entry_points.txt
pibooth_qrcode-1.0.2.dist-info/top_level.txt
pibooth_qrcode-1.0.2.dist-info/RECORD
