Metadata-Version: 2.1
Name: pibooth-qrcode
Version: 1.0.2
Summary: Pibooth plugin to display a QR Code on the screen during idle time.
Home-page: https://github.com/pibooth/pibooth-qrcode
Download-URL: https://github.com/pibooth/pibooth-qrcode/archive/1.0.2.tar.gz
Author: Vincent Verdeil, Antoine Rousseaux
License: GPLv3
Keywords: Raspberry Pi,camera,photobooth,pygame
Platform: unix
Platform: linux
Classifier: Development Status :: 5 - Production/Stable
Classifier: Environment :: Other Environment
Classifier: Intended Audience :: Developers
Classifier: Intended Audience :: End Users/Desktop
Classifier: License :: OSI Approved :: GNU Affero General Public License v3
Classifier: Operating System :: POSIX :: Linux
Classifier: Programming Language :: Python :: 3.6
Classifier: Programming Language :: Python :: 3.7
Classifier: Programming Language :: Python :: 3.8
Classifier: Programming Language :: Python :: 3.9
Classifier: Natural Language :: English
Classifier: Topic :: Multimedia :: Graphics :: Capture :: Digital Camera
Requires-Python: >=3.6
License-File: LICENSE
Requires-Dist: pibooth (>=2.0.0)
Requires-Dist: qrcode (>=6.1)
